CHANGELOG.txt
LICENSE.txt
MANIFEST.in
README.txt
setup.cfg
setup.py
Gallery.egg-info/PKG-INFO
Gallery.egg-info/SOURCES.txt
Gallery.egg-info/dependency_links.txt
Gallery.egg-info/entry_points.txt
Gallery.egg-info/not-zip-safe
Gallery.egg-info/requires.txt
Gallery.egg-info/top_level.txt
doc/index.txt
gallery/__init__.py
gallery/help_strings.py
gallery/plugin.py
gallery/video.png