Metadata-Version: 1.0
Name: Gallery
Version: 0.1.0
Summary: Convert photos and videos for use on the web, integrates with SiteTool to produce static HTML galleries.
Home-page: http://jimmyg.org/work/code/gallery/index.html
Author: James Gardner
Author-email: UNKNOWN
License: GPLv3
Platform: UNKNOWN
